LICENSE.txt
README.md
plasmapdf/__about__.py
plasmapdf/__init__.py
plasmapdf/models/PdfDataLayer.py
plasmapdf/models/__init__.py
plasmapdf/models/types.py
plasmapdf/utils/__init__.py
plasmapdf/utils/utils.py
plasmapdf-0.1.1.dist-info/METADATA
plasmapdf-0.1.1.dist-info/WHEEL
plasmapdf-0.1.1.dist-info/licenses/LICENSE.txt
plasmapdf-0.1.1.dist-info/RECORD
