Metadata-Version: 2.4
Name: plasmapdf
Version: 0.1.1
Summary: Annotation generator and search tools for PDF
Project-URL: Documentation, https://github.com/JSv4/plasmapdf#readme
Project-URL: Issues, https://github.com/JSv4/plasmapdf/issues
Project-URL: Source, https://github.com/JSv4/plasmapdf
Author-email: JSv4 <scrudato@umich.edu>
License: MIT License
License-File: LICENSE.txt
Classifier: Development Status :: 4 - Beta
Classifier: Programming Language :: Python
Classifier: Programming Language :: Python :: 3.10
Classifier: Programming Language :: Python :: 3.11
Classifier: Programming Language :: Python :: 3.12
Classifier: Programming Language :: Python :: Implementation :: CPython
Classifier: Programming Language :: Python :: Implementation :: PyPy
Requires-Python: >=3.10
Requires-Dist: numpy==2.2.1
Requires-Dist: pandas==2.2.3
Requires-Dist: pydantic==2.10.5
